{"rows":[{"City":"Ahmedabad","Lat":23.025793,"Long":72.587265,"w":100},{"City":"Bengaluru","Lat":12.977063,"Long":77.587106,"w":200},{"City":"Bhopal ","Lat":23.254688,"Long":77.402892,"w":400},{"City":"Bhubaneshwar","Lat":20.272411,"Long":85.833853,"w":200},{"City":"Chandigarh ","Lat":30.736292,"Long":76.788398,"w":600},{"City":"Chennai","Lat":13.084622,"Long":80.248357,"w":400},{"City":"Daman","Lat":20.414315,"Long":72.83236,"w":400},{"City":"Gangtok","Lat":27.325739,"Long":88.612155,"w":400},{"City":"Gurugram","Lat":28.460105,"Long":77.026352,"w":400},{"City":"Guwahati","Lat":26.176076,"Long":91.762932,"w":400},{"City":"Hyderabad","Lat":17.384052,"Long":78.456355,"w":400},{"City":"Indore","Lat":22.717736,"Long":75.85859,"w":400},{"City":"Jaipur","Lat":26.913312,"Long":75.787872,"w":400},{"City":"Jammu","Lat":32.735686,"Long":74.869112,"w":400},{"City":"Kolkata ","Lat":22.562627,"Long":88.363044,"w":400},{"City":"Lucknow","Lat":26.839281,"Long":80.923133,"w":400},{"City":"Mumbai","Lat":18.987807,"Long":72.836447,"w":400},{"City":"Nagpur","Lat":21.1458,"Long":79.0882,"w":400},{"City":"New Delhi","Lat":28.6,"Long":77.2,"w":300},{"City":"Panaji","Lat":15.498289,"Long":73.824541},{"City":"Patna","Lat":25.615379,"Long":85.101027},{"City":"Port Blair","Lat":11.666667,"Long":92.75},{"City":"Pune","Lat":18.513271,"Long":73.849852},{"City":"Raipur","Lat":21.233333,"Long":81.633333},{"City":"Ranchi","Lat":23.347768,"Long":85.338564},{"City":"Shiliguri","Lat":26.710035,"Long":88.428512},{"City":"Shillong ","Lat":25.573987,"Long":91.896807},{"City":"Srinagar","Lat":34.085652,"Long":74.805553},{"City":"Thiruvananthapuram","Lat":8.485498,"Long":76.949238}]}